Amal_crawler
setup.py
Amalwebcrawler.egg-info/PKG-INFO
Amalwebcrawler.egg-info/SOURCES.txt
Amalwebcrawler.egg-info/dependency_links.txt
Amalwebcrawler.egg-info/requires.txt
Amalwebcrawler.egg-info/top_level.txt
pymycraawler/__init__.py