Metadata-Version: 1.0
Name: Amalwebcrawler
Version: 0.1
Summary: Web crawler in Python 
Home-page: https://github.com/Roumia/mswl-dt
Author: Amal Roumi Suliman
Author-email: roumia@gmail.com
License: GNU GPLv3
Keywords: web_crawler,MSWL,web_spider,python
Platform: UNKNOWN
